project_extension/__init__.py
project_extension/_version.py
project_extension/handlers.py
project_extension-4.2.5.data/data/etc/jupyter/jupyter_server_config.d/project_extension.json
project_extension-4.2.5.data/data/share/jupyter/labextensions/project_extension/build_log.json
project_extension-4.2.5.data/data/share/jupyter/labextensions/project_extension/package.json
project_extension-4.2.5.data/data/share/jupyter/labextensions/project_extension/static/lib_index_js.7620d53093c96f67159b.js
project_extension-4.2.5.data/data/share/jupyter/labextensions/project_extension/static/lib_index_js.7620d53093c96f67159b.js.map
project_extension-4.2.5.data/data/share/jupyter/labextensions/project_extension/static/remoteEntry.cca667e2f7c6a274e847.js
project_extension-4.2.5.data/data/share/jupyter/labextensions/project_extension/static/remoteEntry.cca667e2f7c6a274e847.js.map
project_extension-4.2.5.data/data/share/jupyter/labextensions/project_extension/static/style.js
project_extension-4.2.5.data/data/share/jupyter/labextensions/project_extension/static/style_index_js.54cb91314b3a1b682b5e.js
project_extension-4.2.5.data/data/share/jupyter/labextensions/project_extension/static/style_index_js.54cb91314b3a1b682b5e.js.map
project_extension-4.2.5.data/data/share/jupyter/labextensions/project_extension/static/vendors-node_modules_axios_index_js.4145fe3f5d66d8d82ea5.js
project_extension-4.2.5.data/data/share/jupyter/labextensions/project_extension/static/vendors-node_modules_axios_index_js.4145fe3f5d66d8d82ea5.js.map
project_extension-4.2.5.data/data/share/jupyter/labextensions/project_extension/install.json
project_extension-4.2.5.dist-info/METADATA
project_extension-4.2.5.dist-info/WHEEL
project_extension-4.2.5.dist-info/entry_points.txt
project_extension-4.2.5.dist-info/licenses/LICENSE
project_extension-4.2.5.dist-info/RECORD
