Metadata-Version: 2.4
Name: project_extension
Version: 4.2.5
Summary: A JupyterLab extension for show project steps
Project-URL: Homepage, https://github.com/GuoYingxu/jupyterlab-projecct-extension.git
Project-URL: Bug Tracker, https://github.com/GuoYingxu/jupyterlab-projecct-extension.git/issues
Project-URL: Repository, https://github.com/GuoYingxu/jupyterlab-projecct-extension.git
Author: GuoYingxu
License: BSD 3-Clause License
License-File: LICENSE
Keywords: extension,itshixun,jupyter,jupyterlab,project
Classifier: Framework :: Jupyter
Classifier: Framework :: Jupyter :: JupyterLab
Classifier: Framework :: Jupyter :: JupyterLab :: 4
Classifier: Framework :: Jupyter :: JupyterLab :: Extensions
Classifier: Framework :: Jupyter :: JupyterLab :: Extensions :: Prebuilt
Classifier: License :: OSI Approved :: BSD License
Classifier: Programming Language :: Python
Classifier: Programming Language :: Python :: 3
Classifier: Programming Language :: Python :: 3.9
Classifier: Programming Language :: Python :: 3.10
Classifier: Programming Language :: Python :: 3.11
Classifier: Programming Language :: Python :: 3.12
Classifier: Programming Language :: Python :: 3.13
Requires-Python: >=3.9
